tikchunk/__init__.py
tikchunk/chunk.py
tikchunk-0.0.5.dist-info/METADATA
tikchunk-0.0.5.dist-info/WHEEL
tikchunk-0.0.5.dist-info/RECORD
