Metadata-Version: 2.4
Name: tikchunk
Version: 0.0.5
Summary: Highly performant python library for recursive semantic text chunking while respecting token limits.
Author: Cody Pedersen
Requires-Python: >=3.12
Requires-Dist: numpy>=2.4.0
Requires-Dist: tiktoken>=0.12.0
